metas_b_least/Example_B_LEAST_1.ipynb
metas_b_least/Example_B_LEAST_2.ipynb
metas_b_least/Example_B_LEAST_3.ipynb
metas_b_least/Example_B_LEAST_MC_1.ipynb
metas_b_least/Example_B_LEAST_MC_2.ipynb
metas_b_least/Example_B_LEAST_MC_3.ipynb
metas_b_least/__init__.py
metas_b_least/metas_b_least.py
metas_b_least/data/b_least_1_data_cal.txt
metas_b_least/data/b_least_1_data_meas.txt
metas_b_least/data/b_least_2_data_cal.txt
metas_b_least/data/b_least_2_data_meas.txt
metas_b_least/data/b_least_3_data_cal.txt
metas_b_least/data/b_least_3_data_meas.txt
metas_b_least-0.6.0.dist-info/LICENSE
metas_b_least-0.6.0.dist-info/METADATA
metas_b_least-0.6.0.dist-info/WHEEL
metas_b_least-0.6.0.dist-info/top_level.txt
metas_b_least-0.6.0.dist-info/RECORD
