Metadata-Version: 2.1
Name: metas-b-least
Version: 0.6.0
Summary: METAS B LEAST is a Python implementation of the B LEAST program of the ISO 6143:2001 norm
Home-page: https://github.com/wollmich/metas-b-least
Author: Michael Wollensack
Author-email: michael.wollensack@metas.ch
License: UNKNOWN
Platform: UNKNOWN
Classifier: Programming Language :: Python :: 3
Classifier: License :: OSI Approved :: MIT License
Classifier: Operating System :: OS Independent
Requires-Dist: numpy
Requires-Dist: scipy
Requires-Dist: matplotlib
